sfn_workflow_client/__init__.py
sfn_workflow_client/config.py
sfn_workflow_client/enums.py
sfn_workflow_client/event.py
sfn_workflow_client/exceptions.py
sfn_workflow_client/execution.py
sfn_workflow_client/util.py
sfn_workflow_client/workflow.py
sfn_workflow_client-1.1.1.dist-info/LICENSE.md
sfn_workflow_client-1.1.1.dist-info/WHEEL
sfn_workflow_client-1.1.1.dist-info/METADATA
sfn_workflow_client-1.1.1.dist-info/RECORD
