Metadata-Version: 2.1
Name: sfn-workflow-client
Version: 1.1.1
Summary: Enhanced, asyncio-compatible client for AWS Step Functions.
Home-page: https://github.com/NarrativeScience/sfn-workflow-client
License: BSD-3-Clause
Author: Jonathan Drake
Author-email: jdrake@narrativescience.com
Requires-Python: >=3.7,<4
Classifier: License :: OSI Approved :: BSD License
Classifier: Programming Language :: Python :: 3
Classifier: Programming Language :: Python :: 3.7
Classifier: Programming Language :: Python :: 3.8
Classifier: Programming Language :: Python :: 3.9
Classifier: Programming Language :: Python :: 3.10
Classifier: Programming Language :: Python :: 3.11
Requires-Dist: aenum (>=3.1.11,<4.0.0)
Requires-Dist: arrow (>=1.2.3,<2.0.0)
Requires-Dist: backoff (>=2.2.1,<3.0.0)
Requires-Dist: boto3 (>=1.24.59,<2.0.0)
Project-URL: Repository, https://github.com/NarrativeScience/sfn-workflow-client
